blockcoin/__init__.py
blockcoin/post.py
blockcoin/session.py
blockcoin/theme.py
blockcoin/user.py
blockcoin/utils.py
blockcoin-0.3.1.dist-info/licenses/LICENSE
blockcoin-0.3.1.dist-info/METADATA
blockcoin-0.3.1.dist-info/WHEEL
blockcoin-0.3.1.dist-info/top_level.txt
blockcoin-0.3.1.dist-info/RECORD
