Metadata-Version: 2.4
Name: blockcoin
Version: 0.3.1
Summary: BlockCoin API Wrapper
Author-email: uukelele-scratch <robustrobot11@gmail.com>
License: MIT
License-File: LICENSE
Requires-Dist: curl_cffi==0.7.4
Dynamic: license-file
